__init__.py
newpy.py
new_py-0.1.2.dist-info/LICENSE
new_py-0.1.2.dist-info/METADATA
new_py-0.1.2.dist-info/WHEEL
new_py-0.1.2.dist-info/entry_points.txt
new_py-0.1.2.dist-info/top_level.txt
new_py-0.1.2.dist-info/RECORD
