Metadata-Version: 2.1
Name: new-py
Version: 0.1.2
Summary: Stub a new Python CLI program
Home-page: https://github.com/kyclark/new.py
Author: Ken Youens-Clark
Author-email: kyclark@gmail.com
License: UNKNOWN
Platform: UNKNOWN
Classifier: Programming Language :: Python :: 3
Classifier: License :: OSI Approved :: MIT License
Classifier: Operating System :: OS Independent
